sndata/__init__.py
sndata/_combine_data.py
sndata/base_classes.py
sndata/exceptions.py
sndata/utils.py
sndata/csp/__init__.py
sndata/csp/_dr1.py
sndata/csp/_dr3.py
sndata/des/__init__.py
sndata/des/_sn3yr.py
sndata/essence/__init__.py
sndata/essence/_narayan16.py
sndata/jla/__init__.py
sndata/jla/_betoule14.py
sndata/loss/__init__.py
sndata/loss/_ganeshalingam13.py
sndata/loss/_load_meta_data.py
sndata/loss/sndb_meta.csv
sndata/sdss/Spectra_txt.zip
sndata/sdss/__init__.py
sndata/sdss/_sako18.py
sndata/sdss/_sako18spec.py
sndata/snls/__init__.py
sndata/snls/_balland09.py
sndata/sweetspot/__init__.py
sndata/sweetspot/_dr1.py
tests/__init__.py
tests/data_parsing_template_tests.py
tests/standard_ui_template_tests.py
tests/test_base_classes.py
tests/test_combined_datasets.py
tests/test_csp.py
tests/test_des.py
tests/test_essence.py
tests/test_exceptions.py
tests/test_jla.py
tests/test_loss.py
tests/test_sdss.py
tests/test_snls.py
tests/test_sweetspot.py
tests/test_utils.py
sndata-1.2.1.dist-info/LICENSE.txt
sndata-1.2.1.dist-info/METADATA
sndata-1.2.1.dist-info/WHEEL
sndata-1.2.1.dist-info/top_level.txt
sndata-1.2.1.dist-info/RECORD
